Metadata-Version: 2.1
Name: mido-fix
Version: 1.2.12
Summary: MIDI Objects for Python
Home-page: https://mido.readthedocs.io/
Author: Ole Martin Bjorndalen
Author-email: ombdalen@gmail.com
License: MIT
Classifier: Development Status :: 5 - Production/Stable
Classifier: Intended Audience :: Developers
Classifier: Natural Language :: English
Classifier: License :: OSI Approved :: MIT License
Classifier: Programming Language :: Python
Classifier: Programming Language :: Python :: 2.7
Classifier: Programming Language :: Python :: 3.6
Provides-Extra: dev
Provides-Extra: ports
License-File: LICENSE
